pyinn/Interpolator.py
pyinn/__init__.py
pyinn/collocation.py
pyinn/dataset_classification.py
pyinn/dataset_regression.py
pyinn/debugging.py
pyinn/main.py
pyinn/model.py
pyinn/plot.py
pyinn/plot_mesh.py
pyinn/train.py
pyinn-0.1.11.dist-info/LICENSE
pyinn-0.1.11.dist-info/METADATA
pyinn-0.1.11.dist-info/WHEEL
pyinn-0.1.11.dist-info/top_level.txt
pyinn-0.1.11.dist-info/RECORD
