Metadata-Version: 2.1
Name: pyinn
Version: 0.1.11
Summary: Interpolating Neural Networks
Author: Chanwook Park
Author-email: chanwookpark2024@u.northwestern.edu
Classifier: Programming Language :: Python :: 3
Classifier: License :: OSI Approved :: MIT License
Classifier: Operating System :: OS Independent
Requires-Python: >=3.6
License-File: LICENSE
